{
	
	"fabulousTargets": {
		"entity": "fab_entity",
		"particles": "fab_particles",
		"weather": "weather",
		"clouds": "clouds",
		"translucent": "fab_translucent"
	},
	"fabulous": {
		"passes": [
			{
				"name": "fab_write",
				"program": "copy",
				"framebuffer": "default",
				"samplerImages": ["entity_main"]
			}
		]
	},

	"beforeWorldRender": {
		"passes": [
			{ "name": "clear_entity", "framebuffer": "entity", "program": "frex_clear" },
			{ "name": "clear_particles", "framebuffer": "particles", "program": "frex_clear" },
			{ "name": "clear_weather","framebuffer": "weather","program": "frex_clear" },
			{ "name": "clear_clouds", "framebuffer": "clouds", "program": "frex_clear" },
			{ "name": "clear_translucent", "framebuffer": "translucent","program": "frex_clear" }
		]
	},
	"images": [
		{
			"name": "reflective",
			"texParams": [
				{ "name": "TEXTURE_MIN_FILTER", "val": "LINEAR" },
				{ "name": "TEXTURE_MAG_FILTER", "val": "LINEAR" },
				{ "name": "TEXTURE_WRAP_S", "val": "CLAMP" },
				{ "name": "TEXTURE_WRAP_T", "val": "CLAMP" }
			]
		},
		{
			"name": "entity_main",
			"texParams": [
				{ "name": "TEXTURE_MIN_FILTER",	"val": "LINEAR" },
				{ "name": "TEXTURE_MAG_FILTER", "val": "LINEAR" },
				{ "name": "TEXTURE_WRAP_S", "val": "CLAMP" },
				{ "name": "TEXTURE_WRAP_T", "val": "CLAMP" }
			]
		},
		{
			"name": "entity_depth",
			"internalFormat": "DEPTH_COMPONENT",
			"pixelFormat": "DEPTH_COMPONENT",
			"pixelDataType": "FLOAT",
			"texParams": [
				{ "name": "TEXTURE_MIN_FILTER", "val": "NEAREST" },
				{ "name": "TEXTURE_MAG_FILTER", "val": "NEAREST" },
				{ "name": "TEXTURE_WRAP_S", "val": "CLAMP" },
				{ "name": "TEXTURE_WRAP_T", "val": "CLAMP" },
				{ "name": "TEXTURE_COMPARE_MODE", "val": "NONE" }
			]
		},
		{
			"name": "particles_main",
			"texParams": [
				{ "name": "TEXTURE_MIN_FILTER", "val": "LINEAR" },
				{ "name": "TEXTURE_MAG_FILTER", "val": "LINEAR" },
				{ "name": "TEXTURE_WRAP_S", "val": "CLAMP" },
				{ "name": "TEXTURE_WRAP_T", "val": "CLAMP" }
			]
		},
		{
			"name": "particles_depth",
			"internalFormat": "DEPTH_COMPONENT",
			"pixelFormat": "DEPTH_COMPONENT",
			"pixelDataType": "FLOAT",
			"texParams": [
				{ "name": "TEXTURE_MIN_FILTER", "val": "NEAREST" },
				{ "name": "TEXTURE_MAG_FILTER", "val": "NEAREST" },
				{ "name": "TEXTURE_WRAP_S", "val": "CLAMP"},
				{ "name": "TEXTURE_WRAP_T", "val": "CLAMP" },
				{ "name": "TEXTURE_COMPARE_MODE", "val": "NONE" }
			]
		},
		{
			"name": "weather_main",
			"texParams": [
				{ "name": "TEXTURE_MIN_FILTER", "val": "LINEAR" },
				{ "name": "TEXTURE_MAG_FILTER", "val": "LINEAR" },
				{ "name": "TEXTURE_WRAP_S", "val": "CLAMP" },
				{ "name": "TEXTURE_WRAP_T", "val": "CLAMP" }
			]
		},
		{
			"name": "weather_depth",
			"internalFormat": "DEPTH_COMPONENT",
			"pixelFormat": "DEPTH_COMPONENT",
			"pixelDataType": "FLOAT",
			"texParams": [
				{ "name": "TEXTURE_MIN_FILTER", "val": "NEAREST" },
				{ "name": "TEXTURE_MAG_FILTER", "val": "NEAREST" },
				{ "name": "TEXTURE_WRAP_S", "val": "CLAMP" },
				{ "name": "TEXTURE_WRAP_T", "val": "CLAMP" },
				{ "name": "TEXTURE_COMPARE_MODE", "val": "NONE" }
			]
		},
		{
			"name": "clouds_main",
			"texParams": [
				{ "name": "TEXTURE_MIN_FILTER", "val": "LINEAR" },
				{ "name": "TEXTURE_MAG_FILTER", "val": "LINEAR" },
				{ "name": "TEXTURE_WRAP_S", "val": "CLAMP" },
				{ "name": "TEXTURE_WRAP_T", "val": "CLAMP" }
			]
		},
		{
			"name": "clouds_depth",
			"internalFormat": "DEPTH_COMPONENT",
			"pixelFormat": "DEPTH_COMPONENT",
			"pixelDataType": "FLOAT",
			"texParams": [
				{ "name": "TEXTURE_MIN_FILTER", "val": "NEAREST" },
				{ "name": "TEXTURE_MAG_FILTER", "val": "NEAREST" },
				{ "name": "TEXTURE_WRAP_S", "val": "CLAMP" },
				{ "name": "TEXTURE_WRAP_T", "val": "CLAMP" },
				{ "name": "TEXTURE_COMPARE_MODE", "val": "NONE" }
			]
		},
		{
			"name": "translucent_main",	
			"texParams": [
				{ "name": "TEXTURE_MIN_FILTER", "val": "LINEAR" },
				{ "name": "TEXTURE_MAG_FILTER", "val": "LINEAR" },
				{ "name": "TEXTURE_WRAP_S", "val": "CLAMP" },
				{ "name": "TEXTURE_WRAP_T", "val": "CLAMP" }
			]
		},
		{
			"name": "translucent_depth",
			"internalFormat": "DEPTH_COMPONENT",
			"pixelFormat": "DEPTH_COMPONENT",
			"pixelDataType": "FLOAT",
			"texParams": [
				{ "name": "TEXTURE_MIN_FILTER", "val": "NEAREST" },
				{ "name": "TEXTURE_MAG_FILTER", "val": "NEAREST" },
				{ "name": "TEXTURE_WRAP_S", "val": "CLAMP" },
				{ "name": "TEXTURE_WRAP_T", "val": "CLAMP" },
				{ "name": "TEXTURE_COMPARE_MODE", "val": "NONE" }
			]
		}
	],
	"framebuffers": [
		{
			"name": "fab_entity",
			"depthAttachment": { "image": "entity_depth" },
			"colorAttachments": [ { "image": "entity_main" } ]
		},
		{
			"name": "fab_particles",
			"depthAttachment": { "image": "particles_depth" },
			"colorAttachments": [ { "image": "particles_main" } ]
		},
		{
			"name": "fab_translucent",
			"depthAttachment": { "image": "translucent_depth" },
			"colorAttachments": [ { "image": "translucent_main" } ]
		},
		{
			"name": "solid",
			"depthAttachment": { "image": "solid_depth" },
			"colorAttachments": [
				{ "image": "solid_main" },
				{ "image": "emissive" },
				{ "image": "reflective" }
			]
		},
		{
			"name": "entity",
			"depthAttachment": { "image": "entity_depth" },
			"colorAttachments": [
				{ "image": "entity_main" },
				{ "image": "emissive" }
			]
		},
		{
			"name": "particles",
			"depthAttachment": { "image": "particles_depth" },
			"colorAttachments": [
				{ "image": "particles_main" },
				{ "image": "emissive" }
			]
		},
		{
			"name": "weather",
			"depthAttachment": { "image": "weather_depth" },
			"colorAttachments": [ { "image": "weather_main" } ]
		},
		{
			"name": "clouds",
			"depthAttachment": { "image": "clouds_depth"},
			"colorAttachments": [
				{ "image": "clouds_main" }
			]
		},
		{
			"name": "translucent",
			"depthAttachment": { "image": "translucent_depth"},
			"colorAttachments": [
				{ "image": "translucent_main", "clearColor": "true" },
				{ "image": "emissive" },
				{ "image": "reflective" }
			]
		}
	]
}